termimg/__init__.py
termimg/__main__.py
termimg/utils.py
termimg/printers/__init__.py
termimg/printers/_base.py
termimg/printers/iterm2.py
termimg/printers/sixel.py
termimg/printers/utf8.py
pytermimg-0.1.0b3.dist-info/METADATA
pytermimg-0.1.0b3.dist-info/WHEEL
pytermimg-0.1.0b3.dist-info/top_level.txt
pytermimg-0.1.0b3.dist-info/RECORD
