Metadata-Version: 2.1
Name: pytermimg
Version: 0.1.0b3
Summary: UNKNOWN
Home-page: UNKNOWN
Author: Yifan Gu
Author-email: dev@yifangu.com
License: MIT
Platform: UNKNOWN
Requires-Python: >3.6
Requires-Dist: pillow (>=8.3.1)
